tdt/__init__.py
tdt/core.py
time_delta_t-0.1.3.dist-info/licenses/LICENSE
time_delta_t-0.1.3.dist-info/METADATA
time_delta_t-0.1.3.dist-info/WHEEL
time_delta_t-0.1.3.dist-info/top_level.txt
time_delta_t-0.1.3.dist-info/RECORD
