Metadata-Version: 2.4
Name: time-delta-t
Version: 0.1.3
Summary: tDt — universal time delta toolkit
Author-email: "Dr. Ippy" <admin@jdplumbingsoflo.com>
License:                                  Apache License
Project-URL: Homepage, https://github.com/JDPlumbing/tdt
Project-URL: Repository, https://github.com/JDPlumbing/tdt
Classifier: Programming Language :: Python :: 3
Classifier: License :: OSI Approved :: Apache Software License
Classifier: Operating System :: OS Independent
Requires-Python: >=3.9
License-File: LICENSE
Requires-Dist: python-dateutil>=2.8
Dynamic: license-file
